loggingtofile/__init__.py
loggingtofile/log.py
loggingtofile-0.0.5.dist-info/LICENSE
loggingtofile-0.0.5.dist-info/METADATA
loggingtofile-0.0.5.dist-info/WHEEL
loggingtofile-0.0.5.dist-info/top_level.txt
loggingtofile-0.0.5.dist-info/RECORD
