Metadata-Version: 2.1
Name: loggingtofile
Version: 0.0.5
Summary: Write logging info to auto-created files.
Home-page: https://github.com/Hideousmon/loggingtofile
Author: Zhenyu ZHAO
Author-email: mailtozyzhao@163.com
License: UNKNOWN
Platform: UNKNOWN
